{
    "Vodafone Limited": [574, "3.27%"],
    "Virgin Media": [3592, "20.48%"],
    "Three": [1122, "6.4%"],
    "BT": [2268, "12.93%"],
    "Sky Broadband": [3995, "22.77%"],
    "Telefonica O2 UK": [1481, "8.44%"],
    "TalkTalk": [2051, "11.69%"],
    "Plusnet": [262, "1.49%"],
    "Metronet (UK) Limited": [4, "0.02%"],
    "EE Mobile": [758, "4.32%"],
    "Privax Ltd.": [7, "0.04%"],
    "EE High Speed Internet": [428, "2.44%"],
    "Vodafone Broadband": [138, "0.79%"],
    "PCCW Global Networks (UK) PLC": [5, "0.03%"],
    "Daisy Communications Ltd": [40, "0.23%"],
    "IFNL": [5, "0.03%"],
    "Topline LLC": [57, "0.32%"],
    "The Cloud Networks Limited": [22, "0.13%"],
    "BT Americas": [26, "0.15%"],
    "The Internexus Group Limited": [8, "0.05%"],
    "other": [86, "0.49%"],
    "Pure Broadband Ltd": [5, "0.03%"],
    "Gamma Telecom Limited": [17, "0.1%"],
    "Centurylink Communications UK Limited": [2, "0.01%"],
    "Lycatel Distribution Uk Limited": [27, "0.15%"],
    "Gamma Telecom Holdings Ltd": [3, "0.02%"],
    "Cablecom Networking": [8, "0.05%"],
    "Virgin Media Business": [24, "0.14%"],
    "Kcom": [123, "0.7%"],
    "Quickline Communications Limited": [4, "0.02%"],
    "Be Un Limited": [3, "0.02%"],
    "Origin Broadband Ltd": [21, "0.12%"],
    "Cogent Communications Group,  Inc.": [7, "0.04%"],
    "Exponential-e": [9, "0.05%"],
    "Razorblue Ltd": [1, "0.01%"],
    "Vodafone": [67, "0.38%"],
    "RIGNET AS": [1, "0.01%"],
    "Vectone Mobile Limited": [2, "0.01%"],
    "RM Education Ltd": [6, "0.03%"],
    "Hyperoptic Ltd": [15, "0.09%"],
    "Zen Internet Ltd": [24, "0.14%"],
    "Digital Ocean": [6, "0.03%"],
    "UK Broadband Ltd.": [1, "0.01%"],
    "Hybrid Access Technologies Limited": [2, "0.01%"],
    "Venus Business Communications Limited": [2, "0.01%"],
    "VoiceHost Ltd": [1, "0.01%"],
    "Luminet Solutions Ltd": [2, "0.01%"],
    "Easynet Enterprise Services Limited": [6, "0.03%"],
    "Connexin Limited": [17, "0.1%"],
    "Hydra Communications Ltd": [3, "0.02%"],
    "Community Fibre Limited": [5, "0.03%"],
    "VData Ltd": [1, "0.01%"],
    "WightFibre Limited": [1, "0.01%"],
    "Adapt Services Limited": [2, "0.01%"],
    "Net365 Ltd": [2, "0.01%"],
    "Eclipse Internet": [11, "0.06%"],
    "Jisc Services Limited": [5, "0.03%"],
    "Evrocom.uk Limited": [1, "0.01%"],
    "Persimmon Homes Ltd.": [5, "0.03%"],
    "CTR Services Uk": [1, "0.01%"],
    "Highland Network Ltd": [2, "0.01%"],
    "Dummy Organisation Object": [1, "0.01%"],
    "SoftLayer Technologies": [1, "0.01%"],
    "iDAQ Ltd.": [1, "0.01%"],
    "Nasstar Group Limited": [1, "0.01%"],
    "Wifinity Ltd": [7, "0.04%"],
    "FastNet International Ltd": [2, "0.01%"],
    "Legaco Networks B.V.": [3, "0.02%"],
    "Contingency Networks Ltd": [2, "0.01%"],
    "AwellConnected.Com": [2, "0.01%"],
    "Premier Choice Telecom Limited": [1, "0.01%"],
    "Icomera AB": [1, "0.01%"],
    "Pure Broadband (infrastructure) Ltd": [1, "0.01%"],
    "Sota Solutions Ltd.": [1, "0.01%"],
    "Ask4 Limited": [1, "0.01%"],
    "Broadband for the Rural North Limited.": [1, "0.01%"],
    "IDE Group Connect Limited": [1, "0.01%"],
    "Claranet Ltd": [6, "0.03%"],
    "Independent Fibre Networks": [1, "0.01%"],
    "Redcentric Managed Solutions Limited": [4, "0.02%"],
    "Block Solutions Ltd": [2, "0.01%"],
    "EliteWork LLC": [1, "0.01%"],
    "Aspire Technology Solutions Ltd": [2, "0.01%"],
    "Swains Limited": [1, "0.01%"],
    "OrbitalNet Ltd": [5, "0.03%"],
    "Wavenet Limited": [1, "0.01%"],
    "Tfm Networks Limited": [2, "0.01%"],
    "SunGard Availability Services (UK) Ltd": [2, "0.01%"],
    "Voiceflex Ltd": [1, "0.01%"],
    "Level 3 Communications": [2, "0.01%"],
    "Fluency Communications Ltd": [1, "0.01%"],
    "Welsh Government": [2, "0.01%"],
    "OVH SAS": [1, "0.01%"],
    "Wightfibre": [4, "0.02%"],
    "Air Broadband Limited": [1, "0.01%"],
    "Go Internet Ltd": [2, "0.01%"],
    "H1 Telekom": [3, "0.02%"],
    "Zscaler": [5, "0.03%"],
    "Entanet": [10, "0.06%"],
    "Wirelesslogic Ltd": [1, "0.01%"],
    "Cogent Communications": [4, "0.02%"],
    "Gigaclear Limited": [3, "0.02%"],
    "Verizon UK Limited": [2, "0.01%"],
    "The Networking People (TNP) Limited": [4, "0.02%"],
    "Gamma Telecom DSL Services": [1, "0.01%"],
    "Man Investments Limited": [1, "0.01%"],
    "Clouvider Limited": [1, "0.01%"],
    "Buz Broadband Limited": [2, "0.01%"],
    "UltraNetworks": [1, "0.01%"],
    "Solway Communications Limited": [2, "0.01%"],
    "MLL Telecom Ltd.": [1, "0.01%"],
    "Independent Fibre Networks Limited": [3, "0.02%"],
    "Virtual1 Limited": [3, "0.02%"],
    "ICUK Computing Services Limited": [4, "0.02%"],
    "Timico Limited": [2, "0.01%"],
    "Vive Technologies Ltd": [1, "0.01%"],
    "CustodianDC Limited": [2, "0.01%"],
    "Internetty Ltd": [1, "0.01%"],
    "Telia Company": [1, "0.01%"],
    "UK2.NET": [2, "0.01%"],
    "Scothosts Limited": [2, "0.01%"],
    "Poundbury Systems Ltd.": [1, "0.01%"],
    "University of Leicester": [1, "0.01%"],
    "De Montfort University": [1, "0.01%"],
    "C.C.S. (Leeds) Ltd": [1, "0.01%"],
    "WiSpire Limited": [1, "0.01%"],
    "Mother Technologies Ltd": [1, "0.01%"],
    "Six Degrees Technology Group Limited": [1, "0.01%"],
    "Airband Community Internet Ltd": [1, "0.01%"],
    "ITS Technology Group": [1, "0.01%"],
    "Canal S SRL": [1, "0.01%"],
    "Purefibre Internet Ltd.": [2, "0.01%"],
    "Awareness Software Limited": [1, "0.01%"],
    "CenturyLink": [2, "0.01%"],
    "STIX Internet Ltd": [1, "0.01%"],
    "ChunkyChips.net Limited": [1, "0.01%"],
    "Interoute Managed Services UK Limited": [1, "0.01%"],
    "5G Communications Ltd": [1, "0.01%"],
    "Durham County Council": [1, "0.01%"],
    "COLT Technology Services Group Limited": [1, "0.01%"],
    "Gamma Network Solution Limited": [1, "0.01%"],
    "SSE PLC": [2, "0.01%"],
    "euNetworks GmbH": [1, "0.01%"],
    "Spitfire Network Services Limited": [1, "0.01%"],
    "Idaq Networks Ltd.": [1, "0.01%"],
    "Plan.com": [2, "0.01%"],
    "web2objects GmbH": [1, "0.01%"],
    "Telstra Limited": [1, "0.01%"],
    "Wightfibre Wireless": [1, "0.01%"],
    "Beacon Broadband LTD": [1, "0.01%"],
    "Vaioni Group Ltd": [1, "0.01%"],
    "Aga Khan University - Institute for the": [1, "0.01%"],
    "BT IT Services Limited": [1, "0.01%"],
    "GCI Network Solutions Limited": [1, "0.01%"],
    "Hampshire County Council": [1, "0.01%"],

    "Convergence (group Networks) Limited": [1, "0.01%"],
    "Operator name": {
        "Total_numbers": [1, "33.43%"],
        "Numbers": [
            3423423432432423,
            24324234324243432,
            2343424324343432,
            423432432432432434,
            23423434343432423
        ]
    }
}
